{
    " ": [
        220, 
        220, 
        220
    ], 
    "!": [
        9, 
        146, 
        104
    ], 
    "\"": [
        224, 
        49, 
        49
    ], 
    "#": [
        43, 
        138, 
        62
    ], 
    "%": [
        169, 
        227, 
        75
    ], 
    "&": [
        102, 
        168, 
        15
    ], 
    "'": [
        240, 
        62, 
        62
    ], 
    "(": [
        230, 
        119, 
        0
    ], 
    ")": [
        27, 
        110, 
        194
    ], 
    "+": [
        197, 
        246, 
        250
    ], 
    ",": [
        255, 
        245, 
        245
    ], 
    "-": [
        32, 
        201, 
        151
    ], 
    ".": [
        12, 
        133, 
        153
    ], 
    "/": [
        255, 
        236, 
        153
    ], 
    "0": [
        34, 
        138, 
        230
    ], 
    "1": [
        255, 
        216, 
        168
    ], 
    "2": [
        255, 
        201, 
        201
    ], 
    "3": [
        130, 
        201, 
        30
    ], 
    "4": [
        163, 
        218, 
        255
    ], 
    "5": [
        77, 
        173, 
        247
    ], 
    "6": [
        21, 
        170, 
        191
    ], 
    "7": [
        255, 
        227, 
        227
    ], 
    "8": [
        244, 
        252, 
        227
    ], 
    "9": [
        255, 
        192, 
        120
    ], 
    ":": [
        92, 
        148, 
        13
    ], 
    ";": [
        253, 
        126, 
        20
    ], 
    "<": [
        233, 
        250, 
        200
    ], 
    "=": [
        34, 
        184, 
        207
    ], 
    ">": [
        8, 
        127, 
        91
    ], 
    "?": [
        217, 
        72, 
        15
    ], 
    "a": [
        102, 
        217, 
        232
    ], 
    "b": [
        24, 
        98, 
        171
    ], 
    "c": [
        28, 
        124, 
        214
    ], 
    "d": [
        255, 
        107, 
        107
    ], 
    "e": [
        59, 
        201, 
        219
    ], 
    "f": [
        192, 
        235, 
        117
    ], 
    "g": [
        255, 
        146, 
        43
    ], 
    "h": [
        252, 
        196, 
        25
    ], 
    "i": [
        201, 
        42, 
        42
    ], 
    "j": [
        148, 
        216, 
        45
    ], 
    "k": [
        56, 
        217, 
        169
    ], 
    "l": [
        235, 
        251, 
        238
    ], 
    "m": [
        114, 
        195, 
        252
    ], 
    "n": [
        204, 
        237, 
        255
    ], 
    "o": [
        11, 
        114, 
        133
    ], 
    "p": [
        50, 
        154, 
        240
    ], 
    "q": [
        250, 
        82, 
        82
    ], 
    "r": [
        232, 
        89, 
        12
    ], 
    "s": [
        255, 
        244, 
        230
    ], 
    "t": [
        81, 
        207, 
        102
    ], 
    "u": [
        178, 
        242, 
        187
    ], 
    "v": [
        211, 
        249, 
        216
    ], 
    "w": [
        255, 
        169, 
        77
    ], 
    "x": [
        105, 
        219, 
        124
    ], 
    "y": [
        140, 
        233, 
        154
    ], 
    "z": [
        247, 
        103, 
        7
    ], 
    "\u00df": [
        55, 
        178, 
        77
    ], 
    "\u00e4": [
        245, 
        159, 
        0
    ], 
    "\u00f6": [
        64, 
        192, 
        87
    ], 
    "\u00fc": [
        195, 
        250, 
        232
    ]
}